README.rst
setup.py
remarkable_tweak/__init__.py
remarkable_tweak/__main__.py
remarkable_tweak/backend.py
remarkable_tweak/frontend.py
remarkable_tweak/ssh.py
remarkable_tweak/system.py
remarkable_tweak.egg-info/PKG-INFO
remarkable_tweak.egg-info/SOURCES.txt
remarkable_tweak.egg-info/dependency_links.txt
remarkable_tweak.egg-info/entry_points.txt
remarkable_tweak.egg-info/not-zip-safe
remarkable_tweak.egg-info/requires.txt
remarkable_tweak.egg-info/top_level.txt