Metadata-Version: 1.1
Name: remarkable-tweak
Version: 0.1.0
Summary: Tweak tool for the reMarkable paper tablet.
Home-page: https://github.com/morngrar/remarkable-tweak
Author: Svein-Kåre Bjørnsen
Author-email: sveinkare@gmail.com
License: GPL
Platform: UNKNOWN
Classifier: Development Status :: 4 - Beta
Classifier: Intended Audience :: End Users/Desktop
Classifier: License :: OSI Approved :: GNU General Public License v3 (GPLv3)
Classifier: Programming Language :: Python :: 3
Classifier: Topic :: Utilities
